rest_avatar/__init__.py
rest_avatar/admin.py
rest_avatar/apps.py
rest_avatar/conf.py
rest_avatar/models.py
rest_avatar/serializers.py
rest_avatar/urls.py
rest_avatar/utils.py
rest_avatar/views.py
rest_avatar/migrations/0001_initial.py
rest_avatar/migrations/__init__.py
rest_avatar/test_utils/__init__.py
rest_avatar/test_utils/test_app/__init__.py
rest_avatar/test_utils/test_app/admin.py
rest_avatar/test_utils/test_app/apps.py
rest_avatar/test_utils/test_app/models.py
rest_avatar/test_utils/test_app/migrations/__init__.py
django_rest_avatar-0.2.0.dist-info/AUTHORS.rst
django_rest_avatar-0.2.0.dist-info/LICENSE
django_rest_avatar-0.2.0.dist-info/METADATA
django_rest_avatar-0.2.0.dist-info/WHEEL
django_rest_avatar-0.2.0.dist-info/top_level.txt
django_rest_avatar-0.2.0.dist-info/RECORD
