Metadata-Version: 2.1
Name: django-rest-avatar
Version: 0.2.0
Summary: A django app for handling user avatars using Django Rest Framework
Home-page: https://github.com/bodgerbarnett/django-rest-avatar
Author: Simon Barnett
Author-email: sbarnett@acresofspace.co.uk
License: BSD
Keywords: django-rest-avatar
Platform: UNKNOWN
Classifier: Development Status :: 3 - Alpha
Classifier: Framework :: Django :: 1.11
Classifier: Framework :: Django :: 2.1
Classifier: Intended Audience :: Developers
Classifier: License :: OSI Approved :: BSD License
Classifier: Natural Language :: English
Classifier: Programming Language :: Python :: 2
Classifier: Programming Language :: Python :: 2.7
Classifier: Programming Language :: Python :: 3
Classifier: Programming Language :: Python :: 3.5
Classifier: Programming Language :: Python :: 3.6
Requires-Dist: django (>=2.2.13)
Requires-Dist: djangorestframework (>=3.10)
Requires-Dist: django-appconf (>=1.0.4)
Requires-Dist: Pillow (>=8.1.0)
